cl57t_raspberry_pi_stepper_drive/CL57TStepperDriver.py
cl57t_raspberry_pi_stepper_drive/_CL57T_GPIO_board.py
cl57t_raspberry_pi_stepper_drive/_CL57T_logger.py
cl57t_raspberry_pi_stepper_drive/_CL57T_math.py
cl57t_raspberry_pi_stepper_drive/_CL57T_move.py
cl57t_raspberry_pi_stepper_drive/_CL57T_reg.py
cl57t_raspberry_pi_stepper_drive/__init__.py
cl57t_raspberry_pi_stepper_drive-0.5.0.dist-info/LICENSE
cl57t_raspberry_pi_stepper_drive-0.5.0.dist-info/METADATA
cl57t_raspberry_pi_stepper_drive-0.5.0.dist-info/WHEEL
cl57t_raspberry_pi_stepper_drive-0.5.0.dist-info/top_level.txt
cl57t_raspberry_pi_stepper_drive-0.5.0.dist-info/RECORD
