Metadata-Version: 2.1
Name: cl57t_raspberry_pi_stepper_drive
Version: 0.5.0
Summary: this is a Python libary to drive a stepper motor with a CL57T stepper driver and a Raspberry Pi
Home-page: https://github.com/iosifnicolae2/cl57t_raspberry_pi_stepper_driver
Author: Nicolae Iosif
Author-email: iosif@bringes.io
Project-URL: Bug Tracker, https://github.com/iosifnicolae2/cl57t_raspberry_pi_stepper_driver/issues
Classifier: Programming Language :: Python :: 3
Classifier: License :: OSI Approved :: GNU General Public License v3 (GPLv3)
Classifier: Operating System :: POSIX :: Linux
Classifier: Development Status :: 4 - Beta
Classifier: Intended Audience :: Developers
Classifier: Natural Language :: English
Classifier: Topic :: System :: Hardware :: Hardware Drivers
Requires-Python: >=3.7
License-File: LICENSE
Requires-Dist: RPi.GPIO
Requires-Dist: pyserial
